SLEEPY/BrukerLoad.py
SLEEPY/ExpSys.py
SLEEPY/GyroRatio.txt
SLEEPY/HamTypes.py
SLEEPY/Hamiltonian.py
SLEEPY/Info.py
SLEEPY/LFrf.py
SLEEPY/Liouvillian.py
SLEEPY/Operators.py
SLEEPY/Para.py
SLEEPY/PowderAvg.py
SLEEPY/Propagator.py
SLEEPY/PwdAvgFuns.py
SLEEPY/RelaxClass.py
SLEEPY/RelaxMat.py
SLEEPY/Rho.py
SLEEPY/Sequence.py
SLEEPY/SpinOp.py
SLEEPY/Tools.py
SLEEPY/__init__.py
SLEEPY/plot_tools.py
SLEEPY/version_info.txt
SLEEPY/vft.py
SLEEPY/PowderFiles/LEBoct31.txt
SLEEPY/PowderFiles/alpha0beta0.txt
SLEEPY/PowderFiles/alpha0beta45.txt
SLEEPY/PowderFiles/alpha0beta90.txt
SLEEPY/PowderFiles/bcr10.txt
SLEEPY/PowderFiles/bcr100.txt
SLEEPY/PowderFiles/bcr20.txt
SLEEPY/PowderFiles/bcr200.txt
SLEEPY/PowderFiles/bcr30.txt
SLEEPY/PowderFiles/bcr40.txt
SLEEPY/PowderFiles/bcr400.txt
SLEEPY/PowderFiles/bcr50.txt
SLEEPY/PowderFiles/bcr80.txt
SLEEPY/PowderFiles/rep10.txt
SLEEPY/PowderFiles/rep100.txt
SLEEPY/PowderFiles/rep144.txt
SLEEPY/PowderFiles/rep168.txt
SLEEPY/PowderFiles/rep20.txt
SLEEPY/PowderFiles/rep2000.txt
SLEEPY/PowderFiles/rep256.txt
SLEEPY/PowderFiles/rep30.txt
SLEEPY/PowderFiles/rep320.txt
SLEEPY/PowderFiles/rep66.txt
SLEEPY/PowderFiles/rep678.txt
SLEEPY/PowderFiles/repoct41.txt
SLEEPY/PowderFiles/zcw143.txt
SLEEPY/PowderFiles/zcw20.txt
SLEEPY/PowderFiles/zcw232.txt
SLEEPY/PowderFiles/zcw28656.txt
SLEEPY/PowderFiles/zcw33.txt
SLEEPY/PowderFiles/zcw376.txt
SLEEPY/PowderFiles/zcw4180.txt
SLEEPY/PowderFiles/zcw54.txt
SLEEPY/PowderFiles/zcw615.txt
SLEEPY/PowderFiles/zcw88.txt
SLEEPY/PowderFiles/zcw986.txt
sleepy_nmr-1.1.1.dist-info/licenses/LICENSE
sleepy_nmr-1.1.1.dist-info/METADATA
sleepy_nmr-1.1.1.dist-info/WHEEL
sleepy_nmr-1.1.1.dist-info/top_level.txt
sleepy_nmr-1.1.1.dist-info/RECORD
