Metadata-Version: 2.4
Name: sleepy-nmr
Version: 1.1.1
Summary: Spins in Liouville-space for rElaxation and Exchange in PYthon
Author: Kai Zumpfe, Albert Smith-Penzel
Author-email: Albert Smith-Penzel <albert.smith-penzel@medizin.uni-leipzig.de>
License: GPL-3.0-or-later
Project-URL: Homepage, https://alsinmr.github.io/SLEEPY
Project-URL: Repository, https://github.com/alsinmr/SLEEPY.git
Project-URL: Issues, https://github.com/alsinmr/SLEEPY/issues
Keywords: NMR,relaxation,exchange,Liouville
Classifier: Programming Language :: Python :: 3
Classifier: Operating System :: OS Independent
Classifier: License :: OSI Approved :: GNU General Public License v3 (GPLv3)
Requires-Python: >=3.7
License-File: LICENSE
Requires-Dist: numpy
Requires-Dist: scipy
Requires-Dist: matplotlib
Dynamic: license-file
